[
 {
  "type": "card",
  "cardId": 0,
  "cardNumber": 0,
  "cardName": "The Fool",
  "cardArcana": "Major Arcana",
  "cardKeywords": ["New beginnings", "spontaneity", "freedom"],
  "uprightMeaning": "Beginnings, innocence, free spirit",
  "reversedMeaning": "Recklessness, fear of the unknown",
  "cardDescription": "A young person standing at the edge of a cliff, full of optimism and potential.",
  "cardElement": "Air",
  "cardPlanet": "Uranus",
  "cardAffirmation": "I trust the journey, even when I do not know the way.",
  "cardColor": "Yellow",
  "cardChakra": "Crown", 
  "cardArchetype": "The Innocent",
  "cardSymbols": ["Cliff", "white rose", "dog", "bundle", "sun"],
  "imageUrl": "images/card_0.jpg"
 },
  {
  "type": "card",
  "cardId": 1,
  "cardNumber": 1,
  "cardName": "The Magician",
  "cardArcana": "Major Arcana",
  "cardKeywords": ["Manifestation", "power", "resourcefulness"],
  "uprightMeaning": "You have the tools to manifest your desires.",
  "reversedMeaning": "Manipulation, illusion, untapped potential",
  "cardDescription": "A figure standing with one hand pointed to the sky and the other to the ground.",
  "cardElement": "Air",
  "cardPlanet": "Mercury",
  "cardAffirmation": "I manifest my reality with focused intention.",
  "cardColor": "Red",
  "cardChakra": "Solar Plexus",
  "cardArchetype": "The Manifestor",
  "cardSymbols": ["Infinity symbol", "wand", "table of elements", "red and white clothing"],
  "imageUrl": "images/card_1.jpg"
  },
  {
  "type": "card",
  "cardId": 2,
  "cardNumber": 2,
  "cardName": "The High Priestess",
  "cardArcana": "Major Arcana",
  "cardKeywords": ["Intuition", "mystery", "subconscious"],
  "uprightMeaning": "Trust your intuition and inner voice.",
  "reversedMeaning": "Disconnected from inner guidance, secrets.",
  "cardDescription": "A woman seated between two pillars with a scroll in her lap, symbolizing hidden knowledge.",
  "cardElement": "Water",
  "cardPlanet": "Moon",
  "cardAffirmation": "I honor the wisdom of my inner voice.",
  "cardColor": "Blue",
  "cardChakra": "Third Eye",
  "cardArchetype": "The Mystic",
  "cardSymbols": ["Pillars", "scroll", "moon crown", "veil with pomegranates"],
  "imageUrl": "images/card_2.jpg"
  },
  {
  "type": "card",
  "cardId": 3,
  "cardNumber": 3,
  "cardName": "The Empress",
  "cardArcana": "Major Arcana",
  "cardKeywords": ["Fertility", "nature", "nurturing"],
  "uprightMeaning": "Abundance, nurturing, creation, divine feminine.",
  "reversedMeaning": "Creative block, dependence on others.",
  "cardDescription": "A regal woman surrounded by nature, symbolizing fertility and Earth energy.",
  "cardElement": "Earth",
  "cardPlanet": "Venus",
  "cardAffirmation": "I nurture myself and others with love and abundance.",
  "cardColor": "Green",
  "cardChakra": "Heart",
  "cardArchetype": "The Mother",
  "cardSymbols": ["Crown of stars", "wheat", "lush forest"],
  "imageUrl": "images/card_3.jpg"
  },
  {
  "type": "card",
  "cardId": 4,
  "cardNumber": 4,
  "cardName": "The Emperor",
  "cardArcana": "Major Arcana",
  "cardKeywords": ["Authority", "structure", "leadership"],
  "uprightMeaning": "Stability, structure, protection, authority.",
  "reversedMeaning": "Domination, rigidity, control issues.",
  "cardDescription": "A powerful ruler seated on a stone throne, symbolizing structure and power.",
  "cardElement": "Fire",
  "cardPlanet": "Aries",
  "cardAffirmation": "I lead with confidence, strength, and purpose.",
  "cardColor": "Red",
  "cardChakra": "Root",
  "cardArchetype": "The Father",
  "cardSymbols": ["Throne", "ram heads", "scepter", "orb"],
  "imageUrl": "images/card_4.jpg"
  },
  {
  "type": "card",
  "cardId": 5,
  "cardNumber": 5,
  "cardName": "The Hierophant",
  "cardArcana": "Major Arcana",
  "cardKeywords": ["Tradition", "wisdom", "spiritual guidance"],
  "uprightMeaning": "Conformity, tradition, spiritual authority.",
  "reversedMeaning": "Rebellion, personal belief, non-conformity.",
  "cardDescription": "A religious figure seated between two pillars, symbolizing sacred knowledge.",
  "cardElement": "Earth",
  "cardPlanet": "Taurus",
  "cardAffirmation": "I seek wisdom from within and from tradition.",
  "cardColor": "White",
  "cardChakra": "Throat",
  "cardArchetype": "The Teacher",
  "cardSymbols": ["Keys", "pillars", "triple cross staff", "acolytes"],
  "imageUrl": "images/card_5.jpg"
  },
  {
  "type": "card",
  "cardId": 6,
  "cardNumber": 6,
  "cardName": "The Lovers",
  "cardArcana": "Major Arcana",
  "cardKeywords": ["Union", "choices", "harmony"],
  "uprightMeaning": "Love, harmony, partnerships, choices.",
  "reversedMeaning": "Imbalance, misalignment of values, disharmony.",
  "cardDescription": "Two figures under an angel, symbolizing divine connection and choices.",
  "cardElement": "Air",
  "cardPlanet": "Gemini",
  "cardAffirmation": "I choose love in all areas of my life.",
  "cardColor": "Pink",
  "cardChakra": "Heart",
  "cardArchetype": "The Beloved",
  "cardSymbols": ["Angel", "sun", "tree of knowledge", "serpent"],
  "imageUrl": "images/card_6.jpg"
  },
  {
  "type": "card",
  "cardId": 7,
  "cardNumber": 7,
  "cardName": "The Chariot",
  "cardArcana": "Major Arcana",
  "cardKeywords": ["Willpower", "determination", "triumph"],
  "uprightMeaning": "Success through determination and control.",
  "reversedMeaning": "Lack of direction, aggression, obstacles.",
  "cardDescription": "A warrior in a chariot pulled by two sphinxes, symbolizing control and forward movement.",
  "cardElement": "Water",
  "cardPlanet": "Cancer",
  "cardAffirmation": "I move forward with confidence and strength.",
  "cardColor": "Black and White",
  "cardChakra": "Solar Plexus",
  "cardArchetype": "The Warrior",
  "cardSymbols": ["Chariot", "armor", "stars", "crescent moons"],
  "imageUrl": "images/card_7.jpg"
  },
  {
  "type": "card",
  "cardId": 8,
  "cardNumber": 8,
  "cardName": "Strength",
  "cardArcana": "Major Arcana",
  "cardKeywords": ["Courage", "compassion", "inner strength"],
  "uprightMeaning": "Inner strength, courage, patience, control.",
  "reversedMeaning": "Self-doubt, weakness, insecurity.",
  "cardDescription": "A woman gently taming a lion, showing strength through compassion.",
  "cardElement": "Fire",
  "cardPlanet": "Leo",
  "cardAffirmation": "My power is rooted in compassion and courage.",
  "cardColor": "Gold",
  "cardChakra": "Heart",
  "cardArchetype": "The Peacemaker",
  "cardSymbols": ["Lion", "infinity symbol", "white robe"],
  "imageUrl": "images/card_8.jpg"
  },
  {
  "type": "card",
  "cardId": 9,
  "cardNumber": 9,
  "cardName": "The Hermit",
  "cardArcana": "Major Arcana",
  "cardKeywords": ["Solitude", "introspection", "guidance"],
  "uprightMeaning": "Soul-searching, inner guidance, contemplation.",
  "reversedMeaning": "Loneliness, isolation, withdrawal.",
  "cardDescription": "An old man carrying a lantern, symbolizing the search for inner wisdom.",
  "cardElement": "Earth",
  "cardPlanet": "Virgo",
  "cardAffirmation": "I find answers by looking within.",
  "cardColor": "Grey",
  "cardChakra": "Third Eye",
  "cardArchetype": "The Sage",
  "cardSymbols": ["Lantern", "cloak", "staff", "mountain top"],
  "imageUrl": "images/card_9.jpg"
  },
  {
  "type": "card",
  "cardId": 10,
  "cardNumber": 10,
  "cardName": "Wheel of Fortune",
  "cardArcana": "Major Arcana",
  "cardKeywords": ["Change", "cycles", "destiny"],
  "uprightMeaning": "Good luck, karma, life cycles, destiny.",
  "reversedMeaning": "Resistance to change, bad luck, setbacks.",
  "cardDescription": "A wheel with symbolic creatures showing the ups and downs of life.",
  "cardElement": "Fire",
  "cardPlanet": "Jupiter",
  "cardAffirmation": "I trust the cycles of life to bring growth and balance.",
  "cardColor": "Gold",
  "cardChakra": "Solar Plexus",
  "cardArchetype": "The Game",
  "cardSymbols": ["Wheel", "sphinx", "snake", "four evangelists"],
  "imageUrl": "images/card_10.jpg"
  },
  {
  "type": "card",
  "cardId": 11,
  "cardNumber": 11,
  "cardName": "Justice",
  "cardArcana": "Major Arcana",
  "cardKeywords": ["Fairness", "truth", "accountability"],
  "uprightMeaning": "Justice, fairness, truth, law.",
  "reversedMeaning": "Dishonesty, unfairness, lack of accountability.",
  "cardDescription": "A figure seated with a sword and scales, symbolizing fairness and balance.",
  "cardElement": "Air",
  "cardPlanet": "Libra",
  "cardAffirmation": "I act with integrity and honor truth.",
  "cardColor": "Blue",
  "cardChakra": "Throat",
  "cardArchetype": "The Judge",
  "cardSymbols": ["Sword", "scales", "pillars", "red robe"],
  "imageUrl": "images/card_11.jpg"
  },
  {
  "type": "card",
  "cardId": 12,
  "cardNumber": 12,
  "cardName": "The Hanged Man",
  "cardArcana": "Major Arcana",
  "cardKeywords": ["Surrender", "perspective", "suspension"],
  "uprightMeaning": "Letting go, new perspective, surrender.",
  "reversedMeaning": "Stalling, resistance, indecision.",
  "cardDescription": "A man hanging upside down by one foot, symbolizing surrender and insight.",
  "cardElement": "Water",
  "cardPlanet": "Neptune",
  "cardAffirmation": "I surrender to growth and embrace new perspectives.",
  "cardColor": "Indigo",
  "cardChakra": "Crown",
  "cardArchetype": "The Martyr",
  "cardSymbols": ["Tree", "halo", "crossed legs", "rope"],
  "imageUrl": "images/card_12.jpg"
  },
  {
  "type": "card",
  "cardId": 13,
  "cardNumber": 13,
  "cardName": "Death",
  "cardArcana": "Major Arcana",
  "cardKeywords": ["Transformation", "endings", "transition"],
  "uprightMeaning": "Endings, change, transformation, renewal.",
  "reversedMeaning": "Fear of change, stagnation, holding on.",
  "cardDescription": "A skeletal figure on horseback, representing the inevitable cycle of life and death.",
  "cardElement": "Water",
  "cardPlanet": "Scorpio",
  "cardAffirmation": "I release the old to make way for the new.",
  "cardColor": "Black",
  "cardChakra": "Root",
  "cardArchetype": "The Transformer",
  "cardSymbols": ["Horse", "black armor", "rising sun", "fallen king"],
  "imageUrl": "images/card_13.jpg"
  },
  {
  "type": "card",
  "cardId": 14,
  "cardNumber": 14,
  "cardName": "Temperance",
  "cardArcana": "Major Arcana",
  "cardKeywords": ["Balance", "moderation", "harmony"],
  "uprightMeaning": "Balance, moderation, patience, purpose.",
  "reversedMeaning": "Imbalance, excess, lack of long-term vision.",
  "cardDescription": "An angel blending two cups, symbolizing harmony and flow.",
  "cardElement": "Fire",
  "cardPlanet": "Sagittarius",
  "cardAffirmation": "I am centered, balanced, and at peace.",
  "cardColor": "White",
  "cardChakra": "Heart",
  "cardArchetype": "The Alchemist",
  "cardSymbols": ["Angel", "water", "Suit of Cups", "triangle in square"],
  "imageUrl": "images/card_14.jpg"
  },
  {
  "type": "card",
  "cardId": 15,
  "cardNumber": 15,
  "cardName": "The Devil",
  "cardArcana": "Major Arcana",
  "cardKeywords": ["Addiction", "materialism", "bondage"],
  "uprightMeaning": "Temptation, attachment, addiction, restriction.",
  "reversedMeaning": "Freedom, release, reclaiming power.",
  "cardDescription": "A horned figure with two people chained, symbolizing control and illusion.",
  "cardElement": "Earth",
  "cardPlanet": "Capricorn",
  "cardAffirmation": "I am free from illusion and empowered by truth.",
  "cardColor": "Black",
  "cardChakra": "Root",
  "cardArchetype": "The Shadow",
  "cardSymbols": ["Chains", "goat", "inverted pentagram", "fire"],
  "imageUrl": "images/card_15.jpg"
  },
  {
  "type": "card",
  "cardId": 16,
  "cardNumber": 16,
  "cardName": "The Tower",
  "cardArcana": "Major Arcana",
  "cardKeywords": ["Sudden change", "upheaval", "awakening"],
  "uprightMeaning": "Revelation, sudden change, chaos.",
  "reversedMeaning": "Avoidance of disaster, fear of change.",
  "cardDescription": "A tower struck by lightning, symbolizing a dramatic shift or awakening.",
  "cardElement": "Fire",
  "cardPlanet": "Mars",
  "cardAffirmation": "I embrace necessary transformation and rebuild with wisdom.",
  "cardColor": "Red",
  "cardChakra": "Solar Plexus",
  "cardArchetype": "The Disruptor",
  "cardSymbols": ["Crumbling tower", "lightning", "falling figures", "flames"],
  "imageUrl": "images/card_16.jpg"
  },
  {
  "type": "card",
  "cardId": 17,
  "cardNumber": 17,
  "cardName": "The Star",
  "cardArcana": "Major Arcana",
  "cardKeywords": ["Hope", "inspiration", "renewal"],
  "uprightMeaning": "Hope, renewal, spirituality, faith.",
  "reversedMeaning": "Despair, lack of faith, disconnection.",
  "cardDescription": "A woman pours water under the stars, symbolizing hope and healing.",
  "cardElement": "Air",
  "cardPlanet": "Aquarius",
  "cardAffirmation": "I am guided by hope and light.",
  "cardColor": "Light Blue",
  "cardChakra": "Crown",
  "cardArchetype": "The Healer",
  "cardSymbols": ["Stars", "water", "naked woman", "ibis"],
  "imageUrl": "images/card_17.jpg"
  },
  {
  "type": "card",
  "cardId": 18,
  "cardNumber": 18,
  "cardName": "The Moon",
  "cardArcana": "Major Arcana",
  "cardKeywords": ["Illusion", "intuition", "subconscious"],
  "uprightMeaning": "Illusion, fear, dreams, subconscious.",
  "reversedMeaning": "Clarity, truth, overcoming fear.",
  "cardDescription": "A path under a moonlit sky, symbolizing mystery and emotional depth.",
  "cardElement": "Water",
  "cardPlanet": "Pisces",
  "cardAffirmation": "I trust my intuition even in the dark.",
  "cardColor": "Silver",
  "cardChakra": "Third Eye",
  "cardArchetype": "The Dreamer",
  "cardSymbols": ["Moon", "dogs", "crayfish", "path"],
  "imageUrl": "images/card_18.jpg"
  },
  {
  "type": "card",
  "cardId": 19,
  "cardNumber": 19,
  "cardName": "The Sun",
  "cardArcana": "Major Arcana",
  "cardKeywords": ["Joy", "success", "positivity"],
  "uprightMeaning": "Happiness, success, vitality, confidence.",
  "reversedMeaning": "Negativity, sadness, unrealistic expectations.",
  "cardDescription": "A child on a white horse beneath the sun, symbolizing joy and abundance.",
  "cardElement": "Fire",
  "cardPlanet": "Sun",
  "cardAffirmation": "I radiate joy and success in all I do.",
  "cardColor": "Yellow",
  "cardChakra": "Solar Plexus",
  "cardArchetype": "The Radiant Child",
  "cardSymbols": ["Sunflowers", "sun", "horse", "banner"],
  "imageUrl": "images/card_19.jpg"
  },
  {
  "type": "card",
  "cardId": 20,
  "cardNumber": 20,
  "cardName": "Judgement",
  "cardArcana": "Major Arcana",
  "cardKeywords": ["Reflection", "reckoning", "inner calling"],
  "uprightMeaning": "Awakening, reflection, reckoning, rebirth.",
  "reversedMeaning": "Self-doubt, inner critic, fear of change.",
  "cardDescription": "Angels sound a trumpet to awaken the dead, symbolizing rebirth and awakening.",
  "cardElement": "Fire",
  "cardPlanet": "Pluto",
  "cardAffirmation": "I rise to meet my highest calling.",
  "cardColor": "White",
  "cardChakra": "Throat",
  "cardArchetype": "The Awakened",
  "cardSymbols": ["Trumpet", "angel", "coffins", "resurrection"],
  "imageUrl": "images/card_20.jpg"
  },
  {
  "type": "card",
  "cardId": 21,
  "cardNumber": 21,
  "cardName": "The World",
  "cardArcana": "Major Arcana",
  "cardKeywords": ["Completion", "fulfillment", "wholeness"],
  "uprightMeaning": "Completion, success, travel, wholeness.",
  "reversedMeaning": "Lack of closure, delays, short cuts.",
  "cardDescription": "A woman dances in a wreath, symbolizing completion and cosmic unity.",
  "cardElement": "Earth",
  "cardPlanet": "Saturn",
  "cardAffirmation": "I celebrate my journey and embrace the whole of life.",
  "cardColor": "Purple",
  "cardChakra": "Crown",
  "cardArchetype": "The Cosmic Dancer",
  "cardSymbols": ["Wreath", "four symbols", "scarf", "naked dancer"],
  "imageUrl": "images/card_21.jpg"
  },
  {
  "type": "card",
  "cardId": 22,
  "cardNumber": 1,
  "cardName": "Ace of Cups",
  "cardArcana": "Suit of Cups",
  "cardKeywords": ["New feelings", "spirituality", "intuition"],
  "uprightMeaning": "Emotional fulfillment, new beginnings in love.",
  "reversedMeaning": "Emotional loss, blocked creativity, emptiness.",
  "cardDescription": "A hand emerges from a cloud holding a cup overflowing with water.",
  "cardElement": "Water",
  "cardPlanet": "Cancer",
  "cardAffirmation": "I open my heart to the flow of love.",
  "cardColor": "Blue",
  "cardChakra": "Heart",
  "cardArchetype": "The Overflow",
  "cardSymbols": ["Cup", "dove", "water", "lotus"],
  "imageUrl": "images/card_22.jpg"
  },
  {
  "type": "card",
  "cardId": 23,
  "cardNumber": 2,
  "cardName": "Two of Cups",
  "cardArcana": "Suit of Cups",
  "cardKeywords": ["Partnership", "connection", "unity"],
  "uprightMeaning": "Unified love, partnership, mutual attraction.",
  "reversedMeaning": "Imbalance, broken communication, tension.",
  "cardDescription": "Two figures exchange cups in a gesture of union.",
  "cardElement": "Water",
  "cardPlanet": "Cancer",
  "cardAffirmation": "I connect deeply with others in harmony.",
  "cardColor": "Pink",
  "cardChakra": "Heart",
  "cardArchetype": "The Lovers",
  "cardSymbols": ["Caduceus", "lion head", "exchange"],
  "imageUrl": "images/card_23.jpg"
  },
  {
  "type": "card",
  "cardId": 24,
  "cardNumber": 3,
  "cardName": "Three of Cups",
  "cardArcana": "Suit of Cups",
  "cardKeywords": ["Celebration", "friendship", "creativity"],
  "uprightMeaning": "Friendship, community, celebration.",
  "reversedMeaning": "Overindulgence, gossip, isolation.",
  "cardDescription": "Three women dance in a circle holding cups high.",
  "cardElement": "Water",
  "cardPlanet": "Cancer",
  "cardAffirmation": "I celebrate life with joy and gratitude.",
  "cardColor": "Orange",
  "cardChakra": "Sacral",
  "cardArchetype": "The Celebration",
  "cardSymbols": ["Dancing women", "fruit", "cups raised"],
  "imageUrl": "images/card_24.jpg"
  },
  {
  "type": "card",
  "cardId": 25,
  "cardNumber": 4,
  "cardName": "Four of Cups",
  "cardArcana": "Suit of Cups",
  "cardKeywords": ["Meditation", "apathy", "reevaluation"],
  "uprightMeaning": "Contemplation, disconnectedness, reevaluation.",
  "reversedMeaning": "Missed opportunities, boredom, self-absorption.",
  "cardDescription": "A person sits under a tree ignoring a cup offered by a hand from a cloud.",
  "cardElement": "Water",
  "cardPlanet": "Cancer",
  "cardAffirmation": "I open myself to new emotional experiences.",
  "cardColor": "Blue",
  "cardChakra": "Heart",
  "cardArchetype": "The Withdrawn",
  "cardSymbols": ["Tree", "cloud", "Suit of Cups"],
  "imageUrl": "images/card_25.jpg"
  },
  {
  "type": "card",
  "cardId": 26,
  "cardNumber": 5,
  "cardName": "Five of Cups",
  "cardArcana": "Suit of Cups",
  "cardKeywords": ["Loss", "regret", "disappointment"],
  "uprightMeaning": "Grief, disappointment, focusing on the negative.",
  "reversedMeaning": "Acceptance, moving on, forgiveness.",
  "cardDescription": "A cloaked figure mourns over spilled cups.",
  "cardElement": "Water",
  "cardPlanet": "Scorpio",
  "cardAffirmation": "I let go of regret and embrace healing.",
  "cardColor": "Indigo",
  "cardChakra": "Solar Plexus",
  "cardArchetype": "The Mourner",
  "cardSymbols": ["Spilled cups", "river", "bridge"],
  "imageUrl": "images/card_26.jpg"
  },
  {
  "type": "card",
  "cardId": 27,
  "cardNumber": 6,
  "cardName": "Six of Cups",
  "cardArcana": "Suit of Cups",
  "cardKeywords": ["Nostalgia", "childhood", "innocence"],
  "uprightMeaning": "Happy memories, healing, innocence.",
  "reversedMeaning": "Stuck in the past, naivety, unrealistic.",
  "cardDescription": "Children exchange cups filled with flowers in a garden.",
  "cardElement": "Water",
  "cardPlanet": "Scorpio",
  "cardAffirmation": "I cherish the beauty of simple joys.",
  "cardColor": "Yellow",
  "cardChakra": "Solar Plexus",
  "cardArchetype": "The Innocents",
  "cardSymbols": ["Children", "flowers", "house"],
  "imageUrl": "images/card_27.jpg"
  },
  {
  "type": "card",
  "cardId": 28,
  "cardNumber": 7,
  "cardName": "Seven of Cups",
  "cardArcana": "Suit of Cups",
  "cardKeywords": ["Choices", "illusion", "fantasy"],
  "uprightMeaning": "Opportunities, imagination, choices.",
  "reversedMeaning": "Temptation, illusion, lack of focus.",
  "cardDescription": "A person faces seven floating cups each containing a different item.",
  "cardElement": "Water",
  "cardPlanet": "Scorpio",
  "cardAffirmation": "I discern my desires with clarity.",
  "cardColor": "Purple",
  "cardChakra": "Third Eye",
  "cardArchetype": "The Dreamer",
  "cardSymbols": ["Floating cups", "clouds", "visions"],
  "imageUrl": "images/card_28.jpg"
  },
  {
  "type": "card",
  "cardId": 29,
  "cardNumber": 8,
  "cardName": "Eight of Cups",
  "cardArcana": "Suit of Cups",
  "cardKeywords": ["Abandonment", "withdrawal", "escapism"],
  "uprightMeaning": "Walking away, letting go, seeking truth.",
  "reversedMeaning": "Avoidance, fear of change, stagnation.",
  "cardDescription": "A person walks away from eight cups into the mountains.",
  "cardElement": "Water",
  "cardPlanet": "Pisces",
  "cardAffirmation": "I walk away to find deeper meaning.",
  "cardColor": "Blue",
  "cardChakra": "Throat",
  "cardArchetype": "The Seeker",
  "cardSymbols": ["Suit of Cups", "moon", "mountain path"],
  "imageUrl": "images/card_29.jpg"
  },
  {
  "type": "card",
  "cardId": 30,
  "cardNumber": 9,
  "cardName": "Nine of Cups",
  "cardArcana": "Suit of Cups",
  "cardKeywords": ["Contentment", "satisfaction", "gratitude"],
  "uprightMeaning": "Emotional fulfillment, satisfaction, gratitude.",
  "reversedMeaning": "Greed, dissatisfaction, indulgence.",
  "cardDescription": "A man sits smugly before nine cups arranged behind him.",
  "cardElement": "Water",
  "cardPlanet": "Pisces",
  "cardAffirmation": "I am grateful for all that brings me joy.",
  "cardColor": "Green",
  "cardChakra": "Heart",
  "cardArchetype": "The Fulfilled",
  "cardSymbols": ["Suit of Cups", "arms crossed", "luxury"],
  "imageUrl": "images/card_30.jpg"
  },
  {
  "type": "card",
  "cardId": 31,
  "cardNumber": 10,
  "cardName": "Ten of Cups",
  "cardArcana": "Suit of Cups",
  "cardKeywords": ["Harmony", "fulfillment", "happiness"],
  "uprightMeaning": "Divine love, family bliss, harmony.",
  "reversedMeaning": "Disconnection, misalignment of values.",
  "cardDescription": "A family dances under a rainbow of ten cups.",
  "cardElement": "Water",
  "cardPlanet": "Pisces",
  "cardAffirmation": "My heart is full of joy and connection.",
  "cardColor": "Rainbow",
  "cardChakra": "Heart",
  "cardArchetype": "The Family",
  "cardSymbols": ["Rainbow", "dancing family", "river"],
  "imageUrl": "images/card_31.jpg"
  },
  {
  "type": "card",
  "cardId": 32,
  "cardNumber": 11,
  "cardName": "Page of Cups",
  "cardArcana": "Suit of Cups",
  "cardKeywords": ["Surprise", "curiosity", "intuition"],
  "uprightMeaning": "Creative opportunities, intuitive messages.",
  "reversedMeaning": "Emotional immaturity, insecurity.",
  "cardDescription": "A young person holds a cup from which a fish emerges.",
  "cardElement": "Water",
  "cardPlanet": "Cancer",
  "cardAffirmation": "I welcome inspiration and emotional insight.",
  "cardColor": "Blue",
  "cardChakra": "Sacral",
  "cardArchetype": "The Messenger",
  "cardSymbols": ["Fish", "cup", "waves"],
  "imageUrl": "images/card_32.jpg"
  },
  {
  "type": "card",
  "cardId": 33,
  "cardNumber": 12,
  "cardName": "Knight of Cups",
  "cardArcana": "Suit of Cups",
  "cardKeywords": ["Romance", "charm", "imagination"],
  "uprightMeaning": "Romantic gesture, beauty, following the heart.",
  "reversedMeaning": "Moodiness, disappointment, unrealistic.",
  "cardDescription": "A knight rides with a cup held forth on a calm horse.",
  "cardElement": "Water",
  "cardPlanet": "Pisces",
  "cardAffirmation": "I follow my heart’s calling with grace.",
  "cardColor": "Silver",
  "cardChakra": "Heart",
  "cardArchetype": "The Romantic",
  "cardSymbols": ["White horse", "armor", "flowing water"],
  "imageUrl": "images/card_33.jpg"
  },
  {
  "type": "card",
  "cardId": 34,
  "cardNumber": 13,
  "cardName": "Queen of Cups",
  "cardArcana": "Suit of Cups",
  "cardKeywords": ["Compassion", "calm", "comfort"],
  "uprightMeaning": "Nurturing, compassion, emotional security.",
  "reversedMeaning": "Martyrdom, insecurity, emotional blocks.",
  "cardDescription": "A serene queen gazes into a decorated cup on her throne.",
  "cardElement": "Water",
  "cardPlanet": "Scorpio",
  "cardAffirmation": "I trust in the strength of compassion.",
  "cardColor": "Aqua",
  "cardChakra": "Heart",
  "cardArchetype": "The Empath",
  "cardSymbols": ["Throne", "ocean", "cup with angels"],
  "imageUrl": "images/card_34.jpg"
  },
  {
  "type": "card",
  "cardId": 35,
  "cardNumber": 14,
  "cardName": "King of Cups",
  "cardArcana": "Suit of Cups",
  "cardKeywords": ["Balance", "diplomacy", "wisdom"],
  "uprightMeaning": "Emotional balance, compassion, control.",
  "reversedMeaning": "Coldness, manipulation, moodiness.",
  "cardDescription": "A king sits on a throne surrounded by water, holding a cup.",
  "cardElement": "Water",
  "cardPlanet": "Pisces",
  "cardAffirmation": "I lead with calm wisdom and emotional strength.",
  "cardColor": "Blue",
  "cardChakra": "Throat",
  "cardArchetype": "The Counselor",
  "cardSymbols": ["Throne", "fish", "ship", "turbulent sea"],
  "imageUrl": "images/card_35.jpg"
  },
  {
  "type": "card",
  "cardId": 36,
  "cardNumber": 1,
  "cardName": "Ace of Wands",
  "cardArcana": "Suit of Wands",
  "cardKeywords": ["Inspiration", "potential", "new beginnings"],
  "uprightMeaning": "A surge of inspiration and creative energy.",
  "reversedMeaning": "Delays, lack of motivation, missed opportunities.",
  "cardDescription": "A hand emerges from a cloud holding a blossoming wand.",
  "cardElement": "Fire",
  "cardPlanet": "Aries",
  "cardAffirmation": "I ignite the flame of my creative power.",
  "cardColor": "Red",
  "cardChakra": "Sacral",
  "cardArchetype": "The Spark",
  "cardSymbols": ["Cloud", "wand", "leaves"],
  "imageUrl": "images/card_36.jpg"
  },
  {
  "type": "card",
  "cardId": 37,
  "cardNumber": 2,
  "cardName": "Two of Wands",
  "cardArcana": "Suit of Wands",
  "cardKeywords": ["Planning", "decisions", "discovery"],
  "uprightMeaning": "Future planning, progress, decisions.",
  "reversedMeaning": "Fear of unknown, lack of planning.",
  "cardDescription": "A figure holding a globe looks out over a landscape.",
  "cardElement": "Fire",
  "cardPlanet": "Aries",
  "cardAffirmation": "I make bold decisions to shape my future.",
  "cardColor": "Orange",
  "cardChakra": "Solar Plexus",
  "cardArchetype": "The Planner",
  "cardSymbols": ["Globe", "Suit of Wands", "balcony"],
  "imageUrl": "images/card_37.jpg"
  },
  {
  "type": "card",
  "cardId": 38,
  "cardNumber": 3,
  "cardName": "Three of Wands",
  "cardArcana": "Suit of Wands",
  "cardKeywords": ["Expansion", "foresight", "opportunity"],
  "uprightMeaning": "Opportunities, vision, confidence.",
  "reversedMeaning": "Obstacles, delays, lack of foresight.",
  "cardDescription": "A person watches ships from a cliff, wands behind.",
  "cardElement": "Fire",
  "cardPlanet": "Aries",
  "cardAffirmation": "I embrace the path that unfolds before me.",
  "cardColor": "Gold",
  "cardChakra": "Solar Plexus",
  "cardArchetype": "The Visionary",
  "cardSymbols": ["Ships", "hills", "robes"],
  "imageUrl": "images/card_38.jpg"
  },
  {
  "type": "card",
  "cardId": 39,
  "cardNumber": 4,
  "cardName": "Four of Wands",
  "cardArcana": "Suit of Wands",
  "cardKeywords": ["Celebration", "harmony", "homecoming"],
  "uprightMeaning": "Joy, celebration, harmony, home.",
  "reversedMeaning": "Tension at home, instability.",
  "cardDescription": "Two figures celebrate under a floral garland between wands.",
  "cardElement": "Fire",
  "cardPlanet": "Aries",
  "cardAffirmation": "I celebrate my victories with loved ones.",
  "cardColor": "Yellow",
  "cardChakra": "Heart",
  "cardArchetype": "The Celebrant",
  "cardSymbols": ["Garland", "castle", "Suit of Wands"],
  "imageUrl": "images/card_39.jpg"
  },
  {
  "type": "card",
  "cardId": 40,
  "cardNumber": 5,
  "cardName": "Five of Wands",
  "cardArcana": "Suit of Wands",
  "cardKeywords": ["Conflict", "competition", "tension"],
  "uprightMeaning": "Challenges, competition, conflict.",
  "reversedMeaning": "Avoidance, tension, disagreements.",
  "cardDescription": "Five people wave wands in what looks like a chaotic scuffle.",
  "cardElement": "Fire",
  "cardPlanet": "Leo",
  "cardAffirmation": "I grow stronger through healthy competition.",
  "cardColor": "Red",
  "cardChakra": "Root",
  "cardArchetype": "The Competitor",
  "cardSymbols": ["Wands clashing", "group"],
  "imageUrl": "images/card_40.jpg"
  },
  {
  "type": "card",
  "cardId": 41,
  "cardNumber": 6,
  "cardName": "Six of Wands",
  "cardArcana": "Suit of Wands",
  "cardKeywords": ["Victory", "recognition", "progress"],
  "uprightMeaning": "Success, recognition, self-confidence.",
  "reversedMeaning": "Egoism, fall from grace, disappointment.",
  "cardDescription": "A figure rides a horse with a victory wreath.",
  "cardElement": "Fire",
  "cardPlanet": "Leo",
  "cardAffirmation": "I celebrate my success with humility and pride.",
  "cardColor": "Gold",
  "cardChakra": "Solar Plexus",
  "cardArchetype": "The Victor",
  "cardSymbols": ["Horse", "crowd", "laurel wreath"],
  "imageUrl": "images/card_41.jpg"
  },
  {
  "type": "card",
  "cardId": 42,
  "cardNumber": 7,
  "cardName": "Seven of Wands",
  "cardArcana": "Suit of Wands",
  "cardKeywords": ["Challenge", "perseverance", "defense"],
  "uprightMeaning": "Courage, standing your ground, resilience.",
  "reversedMeaning": "Overwhelmed, giving up, defensive.",
  "cardDescription": "A person defends themselves from a higher position.",
  "cardElement": "Fire",
  "cardPlanet": "Leo",
  "cardAffirmation": "I stand strong in my truth.",
  "cardColor": "Red",
  "cardChakra": "Root",
  "cardArchetype": "The Defender",
  "cardSymbols": ["Wand raised", "uneven ground"],
  "imageUrl": "images/card_42.jpg"
  },
  {
  "type": "card",
  "cardId": 43,
  "cardNumber": 8,
  "cardName": "Eight of Wands",
  "cardArcana": "Suit of Wands",
  "cardKeywords": ["Speed", "movement", "action"],
  "uprightMeaning": "Swift action, progress, momentum.",
  "reversedMeaning": "Delays, frustration, holding off.",
  "cardDescription": "Eight wands fly through the air toward a destination.",
  "cardElement": "Fire",
  "cardPlanet": "Sagittarius",
  "cardAffirmation": "I move forward with purpose and speed.",
  "cardColor": "Orange",
  "cardChakra": "Sacral",
  "cardArchetype": "The Messenger",
  "cardSymbols": ["Flying wands", "open sky"],
  "imageUrl": "images/card_43.jpg"
  },
  {
  "type": "card",
  "cardId": 44,
  "cardNumber": 9,
  "cardName": "Nine of Wands",
  "cardArcana": "Suit of Wands",
  "cardKeywords": ["Resilience", "boundaries", "persistence"],
  "uprightMeaning": "Determination, last stand, perseverance.",
  "reversedMeaning": "Exhaustion, stubbornness, paranoia.",
  "cardDescription": "A wary figure holds a wand, bandaged and defensive.",
  "cardElement": "Fire",
  "cardPlanet": "Sagittarius",
  "cardAffirmation": "I persevere with strength and courage.",
  "cardColor": "Brown",
  "cardChakra": "Root",
  "cardArchetype": "The Survivor",
  "cardSymbols": ["Bandages", "wall of wands"],
  "imageUrl": "images/card_44.jpg"
  },
  {
  "type": "card",
  "cardId": 45,
  "cardNumber": 10,
  "cardName": "Ten of Wands",
  "cardArcana": "Suit of Wands",
  "cardKeywords": ["Burden", "responsibility", "stress"],
  "uprightMeaning": "Hard work, burden, achievement through struggle.",
  "reversedMeaning": "Burnout, taking on too much, stress.",
  "cardDescription": "A figure struggles under the weight of ten wands.",
  "cardElement": "Fire",
  "cardPlanet": "Sagittarius",
  "cardAffirmation": "I release burdens that no longer serve me.",
  "cardColor": "Brown",
  "cardChakra": "Root",
  "cardArchetype": "The Overburdened",
  "cardSymbols": ["Heavy load", "struggle", "Suit of Wands"],
  "imageUrl": "images/card_45.jpg"
  },
  {
  "type": "card",
  "cardId": 46,
  "cardNumber": 11,
  "cardName": "Page of Wands",
  "cardArcana": "Suit of Wands",
  "cardKeywords": ["Inspiration", "discovery", "free spirit"],
  "uprightMeaning": "Enthusiasm, exploration, new ideas.",
  "reversedMeaning": "Lack of direction, procrastination.",
  "cardDescription": "A young person holds a wand, looking toward the horizon.",
  "cardElement": "Fire",
  "cardPlanet": "Aries",
  "cardAffirmation": "I embrace my creative potential.",
  "cardColor": "Orange",
  "cardChakra": "Sacral",
  "cardArchetype": "The Explorer",
  "cardSymbols": ["Wand", "desert", "enthusiasm"],
  "imageUrl": "images/card_46.jpg"
  },
  {
  "type": "card",
  "cardId": 47,
  "cardNumber": 12,   
  "cardName": "Knight of Wands",
  "cardArcana": "Suit of Wands",
  "cardKeywords": ["Passion", "adventure", "impulsiveness"],
  "uprightMeaning": "Passion, adventure, impulsiveness.",
  "reversedMeaning": "Recklessness, delays, frustration.",
  "cardDescription": "A knight rides a horse with a wand, symbolizing action and adventure.",
  "cardElement": "Fire",
  "cardPlanet": "Sagittarius",
  "cardAffirmation": "I pursue my passions with courage.",
  "cardColor": "Red",
  "cardChakra": "Solar Plexus",
  "cardArchetype": "The Adventurer",
  "cardSymbols": ["Horse", "wand", "desert"],
  "imageUrl": "images/card_47.jpg"
  },
  {
  "type": "card",
  "cardId": 48,
  "cardNumber": 13,
  "cardName": "Queen of Wands",
  "cardArcana": "Suit of Wands",
  "cardKeywords": ["Confidence", "independence", "social butterfly"],
  "uprightMeaning": "Confidence, independence, social butterfly.",
  "reversedMeaning": "Self-doubt, jealousy, lack of self-confidence.",
  "cardDescription": "A queen sits on a throne with a wand, symbolizing confidence and charisma.",
  "cardElement": "Fire",
  "cardPlanet": "Leo",
  "cardAffirmation": "I embrace my inner strength and confidence.",
  "cardColor": "Yellow",
  "cardChakra": "Solar Plexus",
  "cardArchetype": "The Charismatic Leader",
  "cardSymbols": ["Throne", "sunflowers", "wand"],
  "imageUrl": "images/card_48.jpg"
  },
  {
  "type": "card",
  "cardId": 49,
  "cardNumber": 14,
  "cardName": "King of Wands",
  "cardArcana": "Suit of Wands",
  "cardKeywords": ["Leadership", "vision", "entrepreneurship"],
  "uprightMeaning": "Leadership, vision, entrepreneurship.",
  "reversedMeaning": "Impulsiveness, lack of direction, arrogance.",
  "cardDescription": "A king sits on a throne with a wand, symbolizing authority and vision.",
  "cardElement": "Fire",
  "cardPlanet": "Leo",
  "cardAffirmation": "I lead with vision and passion.",
  "cardColor": "Gold",
  "cardChakra": "Solar Plexus",
  "cardArchetype": "The Visionary Leader",
  "cardSymbols": ["Throne", "lion", "wand"],
  "imageUrl": "images/card_49.jpg"
  },
  {
  "type": "card",
  "cardId": 50,
  "cardNumber": 1,  
  "cardName": "Ace of Swords",
  "cardArcana": "Suit of Swords",
  "cardKeywords": ["Clarity", "truth", "new ideas"],
  "uprightMeaning": "New ideas, mental clarity, breakthroughs.",
  "reversedMeaning": "Confusion, chaos, lack of clarity.",
  "cardDescription": "A hand emerges from a cloud holding a sword upright.",
  "cardElement": "Air",
  "cardPlanet": "Gemini",
  "cardAffirmation": "I embrace clarity and truth in my thoughts.",
  "cardColor": "Blue",
  "cardChakra": "Throat",
  "cardArchetype": "The Thinker",
  "cardSymbols": ["Sword", "cloud", "light"],
  "imageUrl": "images/card_50.jpg"
  },
  {
  "type": "card",
  "cardId": 51,
  "cardNumber": 2,
  "cardName": "Two of Swords",
  "cardArcana": "Suit of Swords",
  "cardKeywords": ["Indecision", "choices", "stalemate"],
  "uprightMeaning": "Indecision, choices, stalemate.", 
  "reversedMeaning": "Confusion, information overload.",
  "cardDescription": "A blindfolded figure holds two swords crossed over their heart.",
  "cardElement": "Air",
  "cardPlanet": "Libra",
  "cardAffirmation": "I seek clarity in my decisions.",
  "cardColor": "Grey",
  "cardChakra": "Third Eye",
  "cardArchetype": "The Diplomat",
  "cardSymbols": ["Blindfold", "moon", "Suit of Swords"],
  "imageUrl": "images/card_51.jpg"
  },
  {
  "type": "card",
  "cardId": 52,
  "cardNumber": 3,
  "cardName": "Three of Swords",
  "cardArcana": "Suit of Swords",
  "cardKeywords": ["Heartbreak", "sorrow", "grief"],
  "uprightMeaning": "Heartbreak, sorrow, grief.",  
  "reversedMeaning": "Healing, forgiveness, recovery.",
  "cardDescription": "A heart pierced by three swords, symbolizing heartbreak.",
  "cardElement": "Air",
  "cardPlanet": "Libra",
  "cardAffirmation": "I heal my heart and embrace love.",
  "cardColor": "Black",
  "cardChakra": "Heart",
  "cardArchetype": "The Heartbroken",
  "cardSymbols": ["Suit of Swords", "rain", "heart"],
  "imageUrl": "images/card_52.jpg"
  },
  {
  "type": "card",
  "cardId": 53,
  "cardNumber": 4,
  "cardName": "Four of Swords",
  "cardArcana": "Suit of Swords",
  "cardKeywords": ["Rest", "recovery", "contemplation"],
  "uprightMeaning": "Rest, recovery, contemplation.",
  "reversedMeaning": "Burnout, stagnation, isolation.",
  "cardDescription": "A figure lies on a tomb with swords above, symbolizing rest.",
  "cardElement": "Air",
  "cardPlanet": "Libra",
  "cardAffirmation": "I take time to rest and rejuvenate.",
  "cardColor": "Grey",
  "cardChakra": "Crown",
  "cardArchetype": "The Restorer",
  "cardSymbols": ["Tomb", "Suit of Swords", "stained glass"],
  "imageUrl": "images/card_53.jpg"
  },
  {
  "type": "card",
  "cardId": 54,
  "cardNumber": 5,
  "cardName": "Five of Swords",
  "cardArcana": "Suit of Swords",
  "cardKeywords": ["Conflict", "tension", "betrayal"],
  "uprightMeaning": "Winning at all costs, mind games, tension.",  
  "reversedMeaning": "Resolution, past resentment, moving on.",
  "cardDescription": "A figure holds swords while others walk away in defeat.",
  "cardElement": "Air",
  "cardPlanet": "Aquarius",
  "cardAffirmation": "I choose peace over the need to win.",
  "cardColor": "Silver",
  "cardChakra": "Throat",
  "cardArchetype": "The Victor",
  "cardSymbols": ["Stormy sky", "defeated figures", "smirk"],
  "imageUrl": "images/card_54.jpg"
  },
  {
  "type": "card",
  "cardId": 55,
  "cardNumber": 6,
  "cardName": "Six of Swords",
  "cardArcana": "Suit of Swords",
  "cardKeywords": ["Transition", "rite of passage", "change"],
  "uprightMeaning": "Moving forward, transition, calmer waters.",
  "reversedMeaning": "Resistance to change, unfinished business.",  
  "cardDescription": "A boat carries figures across a body of water.",
  "cardElement": "Air",
  "cardPlanet": "Aquarius",
  "cardAffirmation": "I move toward peace and clarity.",
  "cardColor": "Blue",
  "cardChakra": "Throat",
  "cardArchetype": "The Journey",
  "cardSymbols": ["Boat", "water", "Suit of Swords"],
  "imageUrl": "images/card_55.jpg"
  },
  {
  "type": "card",
  "cardId": 56,
  "cardNumber": 7,
  "cardName": "Seven of Swords",
  "cardArcana": "Suit of Swords",
  "cardKeywords": ["Deception", "betrayal", "stealth"],
  "uprightMeaning": "Strategy, betrayal, hidden dishonor.",
  "reversedMeaning": "Coming clean, rethinking plans.",
  "cardDescription": "A figure sneaks away with five swords.",
  "cardElement": "Air",
  "cardPlanet": "Aquarius",
  "cardAffirmation": "I choose honesty and thoughtful action.",
  "cardColor": "Grey",
  "cardChakra": "Third Eye",
  "cardArchetype": "The Thief",
  "cardSymbols": ["Camp", "sneaking", "Suit of Swords"],
  "imageUrl": "images/card_56.jpg"
  },
  {
  "type": "card",
  "cardId": 57,
  "cardNumber": 8,
  "cardName": "Eight of Swords",
  "cardArcana": "Suit of Swords",
  "cardKeywords": ["Restriction", "fear", "imprisonment"],  
  "uprightMeaning": "Feeling trapped, limiting beliefs, isolation.",
  "reversedMeaning": "Empowerment, seeing options, freedom.",  
  "cardDescription": "A blindfolded figure is bound and surrounded by swords.",
  "cardElement": "Air",
  "cardPlanet": "Gemini",
  "cardAffirmation": "I release my fears and embrace freedom.",
  "cardColor": "Black",
  "cardChakra": "Root",
  "cardArchetype": "The Victim",
  "cardSymbols": ["Blindfold", "Suit of Swords", "water"],
  "imageUrl": "images/card_57.jpg"
  },
  {
  "type": "card",
  "cardId": 58,
  "cardNumber": 9,
  "cardName": "Nine of Swords",
  "cardArcana": "Suit of Swords",
  "cardKeywords": ["Anxiety", "despair", "nightmares"],
  "uprightMeaning": "Worry, guilt, mental anguish.",
  "reversedMeaning": "Hope, reaching out, healing.",
  "cardDescription": "A person sits up in bed, face in hands, with nine swords on the wall.",
  "cardElement": "Air",
  "cardPlanet": "Gemini",
  "cardAffirmation": "I release my fears and find peace.",
  "cardColor": "Black",
  "cardChakra": "Crown",
  "cardArchetype": "The Worried",
  "cardSymbols": ["Bed", "darkness", "swords on wall"],
  "imageUrl": "images/card_58.jpg"
  },
  {
  "type": "card",
  "cardId": 59,
  "cardNumber": 10,
  "cardName": "Ten of Swords",
  "cardArcana": "Suit of Swords",
  "cardKeywords": ["Defeat", "endings", "betrayal"],
  "uprightMeaning": "Painful endings, deep wounds, collapse.",
  "reversedMeaning": "Recovery, regeneration, forgiveness.",
  "cardDescription": "A figure lies face down with ten swords in their back.",
  "cardElement": "Air",
  "cardPlanet": "Gemini",
  "cardAffirmation": "I release the past and embrace a new dawn.",
  "cardColor": "Crimson",
  "cardChakra": "Root",
  "cardArchetype": "The Martyr",
  "cardSymbols": ["Dawn sky", "prone figure", "multiple swords"],
  "imageUrl": "images/card_59.jpg"
  },
  {
  "type": "card",
  "cardId": 60,
  "cardNumber": 11,
  "cardName": "Page of Swords",
  "cardArcana": "Suit of Swords",
  "cardKeywords": ["Curiosity", "vigilance", "communication"],
  "uprightMeaning": "New ideas, curiosity, mental energy.",
  "reversedMeaning": "Deception, manipulation, haste.",
  "cardDescription": "A youth holds a sword alertly while scanning the horizon.",
  "cardElement": "Air",
  "cardPlanet": "Libra",
  "cardAffirmation": "I explore knowledge with clarity and honesty.",
  "cardColor": "Light Blue",
  "cardChakra": "Throat",
  "cardArchetype": "The Student",
  "cardSymbols": ["Clouds", "wind", "upright sword"],
  "imageUrl": "images/card_60.jpg"
  },
  {
  "type": "card",
  "cardId": 61,
  "cardNumber": 12,
  "cardName": "Knight of Swords",
  "cardArcana": "Suit of Swords",
  "cardKeywords": ["Action", "ambition", "haste"],
  "uprightMeaning": "Swift action, ambition, charging ahead.",
  "reversedMeaning": "Impulsiveness, aggression, reckless.",
  "cardDescription": "A knight charges forward on horseback with sword raised.",
  "cardElement": "Air",
  "cardPlanet": "Gemini",
  "cardAffirmation": "I act decisively and with honor.",
  "cardColor": "Grey",
  "cardChakra": "Solar Plexus",
  "cardArchetype": "The Charger",
  "cardSymbols": ["Galloping horse", "clouds", "sword raised"],
  "imageUrl": "images/card_61.jpg"
  },
  {
  "type": "card",
  "cardId": 62,
  "cardNumber": 13,
  "cardName": "Queen of Swords",
  "cardArcana": "Suit of Swords",
  "cardKeywords": ["Intelligence", "truth", "direct communication"],
  "uprightMeaning": "Clear thinking, independence, unbiased judgment.",
  "reversedMeaning": "Harsh judgment, bitterness, cold.",
  "cardDescription": "A queen sits on her throne holding a sword upright.",
  "cardElement": "Air",
  "cardPlanet": "Virgo",
  "cardAffirmation": "I speak truth with grace and wisdom.",
  "cardColor": "White",
  "cardChakra": "Throat",
  "cardArchetype": "The Wise Woman",
  "cardSymbols": ["Throne", "clouds", "butterfly"],
  "imageUrl": "images/card_62.jpg"
  },
  {
  "type": "card",
  "cardId": 63,
  "cardNumber": 14,
  "cardName": "King of Swords",
  "cardArcana": "Suit of Swords",
  "cardKeywords": ["Authority", "truth", "intellectual power"],
  "uprightMeaning": "Mental clarity, intellectual power, authority.",
  "reversedMeaning": "Abuse of power, manipulation, cruelty.",
  "cardDescription": "A king sits on his throne holding a sword upright.",
  "cardElement": "Air",
  "cardPlanet": "Capricorn",
  "cardAffirmation": "I rule with logic and fairness.",
  "cardColor": "Silver",
  "cardChakra": "Throat",
  "cardArchetype": "The Strategist",
  "cardSymbols": ["Throne", "trees", "birds"],
  "imageUrl": "images/card_63.jpg"
  },
  {
  "type": "card",
  "cardId": 64,
  "cardNumber": 1,
  "cardName": "Ace of Pentacles",
  "cardArcana": "Suit of Pentacles",
  "cardKeywords": ["Opportunity", "prosperity", "new venture"],
  "uprightMeaning": "New financial opportunity, prosperity, abundance.",
  "reversedMeaning": "Lost opportunity, missed chance, scarcity.",
  "cardDescription": "A hand emerges from a cloud holding a large gold coin.",
  "cardElement": "Earth",
  "cardPlanet": "Capricorn",
  "cardAffirmation": "I am open to receiving abundance.",
  "cardColor": "Green",
  "cardChakra": "Root",
  "cardArchetype": "The Seed",
  "cardSymbols": ["Garden", "pentacle", "lilies"],
  "imageUrl": "images/card_64.jpg"
  },
  {
  "type": "card",
  "cardId": 65,
  "cardNumber": 2,
  "cardName": "Two of Pentacles",
  "cardArcana": "Suit of Pentacles",
  "cardKeywords": ["Balance", "adaptability", "flexibility"],
  "uprightMeaning": "Juggling priorities, adaptability, balance.",
  "reversedMeaning": "Imbalance, disorganization, overwhelm.",
  "cardDescription": "A figure juggles two pentacles in a figure-eight pattern.",
  "cardElement": "Earth",
  "cardPlanet": "Capricorn",
  "cardAffirmation": "I adapt with grace and keep my balance.",
  "cardColor": "Brown",
  "cardChakra": "Root",
  "cardArchetype": "The Juggler",
  "cardSymbols": ["Infinity symbol", "ships", "dancing figure"],
  "imageUrl": "images/card_65.jpg"
  },
  {
  "type": "card",
  "cardId": 66,
  "cardNumber": 3,
  "cardName": "Three of Pentacles",
  "cardArcana": "Suit of Pentacles",
  "cardKeywords": ["Teamwork", "collaboration", "craftsmanship"],
  "uprightMeaning": "Teamwork, learning, skill.",
  "reversedMeaning": "Lack of teamwork, disorganization, lack of focus.",
  "cardDescription": "A craftsman works with others inside a monastery.",
  "cardElement": "Earth",
  "cardPlanet": "Capricorn",
  "cardAffirmation": "I build something lasting with others.",
  "cardColor": "Grey",
  "cardChakra": "Root",
  "cardArchetype": "The Builder",
  "cardSymbols": ["Architectural plans", "workers", "monastery"],
  "imageUrl": "images/card_66.jpg"
  },
  {
  "type": "card",
  "cardId": 67,
  "cardNumber": 4,
  "cardName": "Four of Pentacles",
  "cardArcana": "Suit of Pentacles",
  "cardKeywords": ["Conservation", "security", "control"],
  "uprightMeaning": "Saving money, security, conservatism.",
  "reversedMeaning": "Greed, materialism, hoarding.",
  "cardDescription": "A figure clings to four coins defensively.",
  "cardElement": "Earth",
  "cardPlanet": "Capricorn",
  "cardAffirmation": "I am secure and generous with my wealth.",
  "cardColor": "Black",
  "cardChakra": "Root",
  "cardArchetype": "The Holder",
  "cardSymbols": ["Crown coin", "embraced coin", "foot coins", "city", "tight grip"],
  "imageUrl": "images/card_67.jpg"
  },
  {
  "type": "card",
  "cardId": 68,
  "cardNumber": 5,
  "cardName": "Five of Pentacles",
  "cardArcana": "Suit of Pentacles",
  "cardKeywords": ["Isolation", "insecurity", "worry"],
  "uprightMeaning": "Hardship, poverty, insecurity.",
  "reversedMeaning": "Recovery, improvement.",
  "cardDescription": "Two figures struggle in snow outside a lit church.",
  "cardElement": "Earth",
  "cardPlanet": "Taurus",
  "cardAffirmation": "I seek help and find hope in the darkness.",
  "cardColor": "Dark Green",
  "cardChakra": "Root",
  "cardArchetype": "The Outcast",
  "cardSymbols": ["Snow", "crutches", "church window"],
  "imageUrl": "images/card_68.jpg"
  },
  {
  "type": "card",
  "cardId": 69,
  "cardNumber": 6,
  "cardName": "Six of Pentacles",
  "cardArcana": "Suit of Pentacles",
  "cardKeywords": ["Generosity", "sharing", "balance"],
  "uprightMeaning": "Charity, sharing wealth, generosity.",
  "reversedMeaning": "Strings attached, debt.",
  "cardDescription": "A wealthy man gives coins to the poor.",
  "cardElement": "Earth",
  "cardPlanet": "Taurus",
  "cardAffirmation": "I give and receive in balance.",
  "cardColor": "Gold",
  "cardChakra": "Heart",
  "cardArchetype": "The Giver",
  "cardSymbols": ["Scales", "beggars", "coins"],
  "imageUrl": "images/card_69.jpg"
  },
  {
  "type": "card",
  "cardId": 70,
  "cardNumber": 7,
  "cardName": "Seven of Pentacles",
  "cardArcana": "Suit of Pentacles",
  "cardKeywords": ["Assessment", "patience", "planning"],
  "uprightMeaning": "Long-term view, perseverance, reward.",
  "reversedMeaning": "Lack of reward, impatience.",
  "cardDescription": "A figure leans on a tool and looks at a growing plant.",
  "cardElement": "Earth",
  "cardPlanet": "Taurus",
  "cardAffirmation": "I trust the process and practice patience.",
  "cardColor": "Brown",
  "cardChakra": "Root",
  "cardArchetype": "The Gardener",
  "cardSymbols": ["Bush", "Suit of Pentacles", "reflection"],
  "imageUrl": "images/card_70.jpg"
  },
  {
  "type": "card",
  "cardId": 71,
  "cardNumber": 8,
  "cardName": "Eight of Pentacles",
  "cardArcana": "Suit of Pentacles",
  "cardKeywords": ["Skill development", "mastery", "craftsmanship"],
  "uprightMeaning": "Diligence, mastering a skill, craftsmanship.",
  "reversedMeaning": "Laziness, lack of ambition.",
  "cardDescription": "A person carefully carves pentacles on a bench.",
  "cardElement": "Earth",
  "cardPlanet": "Virgo",
  "cardAffirmation": "I master my craft through dedication.",
  "cardColor": "Beige",
  "cardChakra": "Solar Plexus",
  "cardArchetype": "The Apprentice",
  "cardSymbols": ["Workbench", "carvings"],
  "imageUrl": "images/card_71.jpg"
  },
  {
  "type": "card",
  "cardId": 72,
  "cardNumber": 9,
  "cardName": "Nine of Pentacles",
  "cardArcana": "Suit of Pentacles",
  "cardKeywords": ["Luxury", "self-sufficiency", "refinement"],
  "uprightMeaning": "Abundance, luxury, self-sufficiency.",
  "reversedMeaning": "Overindulgence, dependence.",
  "cardDescription": "A woman stands in a lush garden with a falcon.",
  "cardElement": "Earth",
  "cardPlanet": "Virgo",
  "cardAffirmation": "I enjoy the fruits of my labor.",
  "cardColor": "Green",
  "cardChakra": "Heart",
  "cardArchetype": "The Independent",
  "cardSymbols": ["Garden", "grapes", "falcon"],
  "imageUrl": "images/card_72.jpg"
  },
  {
  "type": "card",
  "cardId": 73,
  "cardNumber": 10,
  "cardName": "Ten of Pentacles",
  "cardArcana": "Suit of Pentacles",
  "cardKeywords": ["Legacy", "inheritance", "culmination"],
  "uprightMeaning": "Wealth, family, long-term success.",
  "reversedMeaning": "Financial failure, instability.",
  "cardDescription": "An elderly man sits with family and dogs around him.",
  "cardElement": "Earth",
  "cardPlanet": "Virgo",
  "cardAffirmation": "I build a legacy of love and stability.",
  "cardColor": "Gold",
  "cardChakra": "Root",
  "cardArchetype": "The Legacy",
  "cardSymbols": ["Castle", "archway", "coins"],
  "imageUrl": "images/card_73.jpg"
  },
  {
  "type": "card",
  "cardId": 74,
  "cardNumber": 11,
  "cardName": "Page of Pentacles",
  "cardArcana": "Suit of Pentacles",
  "cardKeywords": ["Ambition", "diligence", "new ventures"],
  "uprightMeaning": "Manifestation, financial opportunity, skill development.",
  "reversedMeaning": "Laziness, lack of progress.",
  "cardDescription": "A young person studies a coin with focus.",
  "cardElement": "Earth",
  "cardPlanet": "Taurus",
  "cardAffirmation": "I take practical steps toward my dreams.",
  "cardColor": "Olive",
  "cardChakra": "Root",
  "cardArchetype": "The Student",
  "cardSymbols": ["Fields", "pentacle", "concentration"],
  "imageUrl": "images/card_74.jpg"
  },
  {
  "type": "card",
  "cardId": 75,
  "cardNumber": 12,
  "cardName": "Knight of Pentacles",
  "cardArcana": "Suit of Pentacles",
  "cardKeywords": ["Efficiency", "responsibility", "routine"],
  "uprightMeaning": "Hard work, responsibility, productivity.",
  "reversedMeaning": "Laziness, obsessiveness.",
  "cardDescription": "A knight holds a coin and sits on a motionless horse.",
  "cardElement": "Earth",
  "cardPlanet": "Virgo",
  "cardAffirmation": "I move steadily with purpose and care.",
  "cardColor": "Brown",
  "cardChakra": "Root",
  "cardArchetype": "The Worker",
  "cardSymbols": ["Plowed field", "armor", "horse"],
  "imageUrl": "images/card_75.jpg"
  },
  {
  "type": "card",
  "cardId": 76,
  "cardNumber": 13,
  "cardName": "Queen of Pentacles",
  "cardArcana": "Suit of Pentacles",
  "cardKeywords": ["Nurturing", "practicality", "security"],
  "uprightMeaning": "Motherly, practical, grounded.",
  "reversedMeaning": "Imbalance, smothering, financial dependence.",
  "cardDescription": "A queen sits holding a coin amidst nature.",
  "cardElement": "Earth",
  "cardPlanet": "Capricorn",
  "cardAffirmation": "I nurture abundance in my world.",
  "cardColor": "Green",
  "cardChakra": "Heart",
  "cardArchetype": "The Provider",
  "cardSymbols": ["Throne", "bunny", "flowers"],
  "imageUrl": "images/card_76.jpg"
  },
  {
  "type": "card",
  "cardId": 77,
  "cardNumber": 14,
  "cardName": "King of Pentacles",
  "cardArcana": "Suit of Pentacles",
  "cardKeywords": ["Abundance", "security", "leadership"],
  "uprightMeaning": "Wealth, leadership, security.",
  "reversedMeaning": "Stubbornness, greed.",
  "cardDescription": "A king sits on a throne adorned with grapes and bull motifs.",
  "cardElement": "Earth",
  "cardPlanet": "Taurus",
  "cardAffirmation": "I lead with wisdom and prosperity.",
  "cardColor": "Gold",
  "cardChakra": "Root",
  "cardArchetype": "The Patron",
  "cardSymbols": ["Throne", "castle", "fruit"],
  "imageUrl": "images/card_77.jpg"
  }
  ]
  
